{
  "notes": "Moet-selected locked temp voice set for autonomous execution. Chosen to preserve clean separation and avoid novelty drift.",
  "characters": {
    "Mon": {
      "provider": "say",
      "voice": "Shelley (English (US))",
      "tts_rate": 180,
      "intent": "clear, precise, controlled"
    },
    "Chance": {
      "provider": "say",
      "voice": "Eddy (English (US))",
      "tts_rate": 176,
      "intent": "dry, amused, understated"
    },
    "Russ": {
      "provider": "say",
      "voice": "Reed (English (US))",
      "tts_rate": 182,
      "intent": "warm, earnest, slightly anxious"
    },
    "Rachelle": {
      "provider": "say",
      "voice": "Sandy (English (US))",
      "tts_rate": 182,
      "intent": "polished, observant, lightly amused"
    },
    "Jojo": {
      "provider": "say",
      "voice": "Flo (English (US))",
      "tts_rate": 186,
      "intent": "warm, open, easygoing"
    },
    "Fufu": {
      "provider": "say",
      "voice": "Samantha",
      "tts_rate": 194,
      "intent": "bright, expressive, delighted by chaos"
    }
  }
}
